{
  "main": {
    "id": "d5d83da524d87984",
    "type": "split",
    "children": [
      {
        "id": "cb1804dffc7f28df",
        "type": "tabs",
        "children": [
          {
            "id": "94965ccc10428bf1",
            "type": "leaf",
            "state": {
              "type": "empty",
              "state": {},
              "icon": "lucide-file",
              "title": "New tab"
            }
          }
        ]
      }
    ],
    "direction": "vertical"
  },
  "left": {
    "id": "08887be90a7ae360",
    "type": "split",
    "children": [
      {
        "id": "bfe3da4fdf9c8d69",
        "type": "tabs",
        "dimension": 72.12121212121212,
        "children": [
          {
            "id": "a1fa3e45c64556dc",
            "type": "leaf",
            "state": {
              "type": "file-explorer",
              "state": {
                "sortOrder": "alphabetical",
                "autoReveal": false
              },
              "icon": "lucide-folder-closed",
              "title": "Files"
            }
          },
          {
            "id": "2e7f17803935dfed",
            "type": "leaf",
            "state": {
              "type": "search",
              "state": {
                "query": "",
                "matchingCase": false,
                "explainSearch": false,
                "collapseAll": false,
                "extraContext": false,
                "sortOrder": "alphabetical"
              },
              "icon": "lucide-search",
              "title": "Search"
            }
          },
          {
            "id": "dd97c468464316fa",
            "type": "leaf",
            "state": {
              "type": "bookmarks",
              "state": {},
              "icon": "lucide-bookmark",
              "title": "Bookmarks"
            }
          }
        ]
      },
      {
        "id": "47f31d4b60b06bf0",
        "type": "tabs",
        "dimension": 27.878787878787882,
        "children": [
          {
            "id": "0a8ff5da2585b067",
            "type": "leaf",
            "state": {
              "type": "graph",
              "state": {},
              "icon": "lucide-git-fork",
              "title": "Graph view"
            }
          }
        ]
      }
    ],
    "direction": "horizontal",
    "width": 300
  },
  "right": {
    "id": "1b82e143d46a10a9",
    "type": "split",
    "children": [
      {
        "id": "be3fdd7a774c504e",
        "type": "tabs",
        "dimension": 64.05038759689923,
        "children": [
          {
            "id": "0c3d03784ee9600e",
            "type": "leaf",
            "state": {
              "type": "backlink",
              "state": {
                "collapseAll": false,
                "extraContext": false,
                "sortOrder": "alphabetical",
                "showSearch": false,
                "searchQuery": "",
                "backlinkCollapsed": false,
                "unlinkedCollapsed": true
              },
              "icon": "links-coming-in",
              "title": "Backlinks"
            }
          },
          {
            "id": "6fc9df6571515f6e",
            "type": "leaf",
            "state": {
              "type": "outgoing-link",
              "state": {
                "linksCollapsed": false,
                "unlinkedCollapsed": true
              },
              "icon": "links-going-out",
              "title": "Outgoing links"
            }
          },
          {
            "id": "6a53b84133dc7da0",
            "type": "leaf",
            "state": {
              "type": "tag",
              "state": {
                "sortOrder": "frequency",
                "useHierarchy": true,
                "showSearch": false,
                "searchQuery": ""
              },
              "icon": "lucide-tags",
              "title": "Tags"
            }
          },
          {
            "id": "af73fdbe015ca896",
            "type": "leaf",
            "state": {
              "type": "outline",
              "state": {
                "followCursor": true,
                "showSearch": false,
                "searchQuery": ""
              },
              "icon": "lucide-list",
              "title": "Outline"
            }
          }
        ],
        "currentTab": 2
      },
      {
        "id": "d2df58ed645172c4",
        "type": "tabs",
        "dimension": 35.94961240310077,
        "children": [
          {
            "id": "a5e2866382ffd6d0",
            "type": "leaf",
            "state": {
              "type": "calendar",
              "state": {},
              "icon": "calendar-with-checkmark",
              "title": "Calendar"
            }
          }
        ]
      }
    ],
    "direction": "horizontal",
    "width": 300
  },
  "left-ribbon": {
    "hiddenItems": {
      "switcher:Open quick switcher": false,
      "graph:Open graph view": false,
      "canvas:Create new canvas": false,
      "daily-notes:Open today's daily note": false,
      "templates:Insert template": false,
      "command-palette:Open command palette": false,
      "bases:Create new base": false
    }
  },
  "active": "6a53b84133dc7da0",
  "lastOpenFiles": [
    "Welcome.md"
  ]
}